{"distribution": "lg", "edges": [["A", "D"], ["B", "D"], ["D", "E"], ["C", "E"]], "root_params": "A ~ N(20,20) B ~ N(20,20) C ~ N(15,15)", "experiment": 101, "not_root_params": "D   ~   N ( 2 A + 3 B , 1 . 0 )   E   ~   N ( 3 C + 3 D , 1 . 0 )", "sample_size": 100, "means": {"A": 20, "B": 20, "C": 15, "D": 100, "E": 345}, "disc_method": "EV", "bins": 25, "target_column": null, "CPT_method": "MLE", "time_disc": 0.08588400902226567, "time_cnf": 1.3952446281909943, "time_VE": 0.0020869970321655273, "time_BP": 0.01010721456259489, "RMSE": 4.969363947224674, "WRMSE": 4.969363947224675, "MAE": 3.8409656104432224, "PE": 0.04148827165171615, "exact_EV": 345, "disc_EV": 344.8568654628016, "Wass_scaled": 0.10318616893500845, "Wass_multi": 0.6797108181961815, "time_wass": 0.018433379009366035}