{"distribution": "lg", "edges": [["A", "D"], ["B", "D"], ["D", "E"], ["C", "E"]], "root_params": "A ~ N(20,20) B ~ N(20,20) C ~ N(15,15)", "experiment": 120, "not_root_params": "D   ~   N ( 2 A + 3 B , 7 . 4 6 8 7 5 )   E   ~   N ( 3 C + 3 D , 7 . 4 6 8 7 5 )", "sample_size": 753, "means": {"A": 20, "B": 20, "C": 15, "D": 100, "E": 345}, "disc_method": "EV", "bins": 8, "target_column": null, "CPT_method": "MLE", "time_disc": 0.07241272507235408, "time_cnf": 0.1829573241993785, "time_VE": 0.0035681077279150486, "time_BP": 0.008555194828659296, "RMSE": 3.787917603573202, "WRMSE": 3.787396277559178, "MAE": 2.675795903235226, "PE": 0.3545938890457476, "exact_EV": 345, "disc_EV": 343.77665108279217, "Wass_scaled": 0.29917173446216483, "Wass_multi": 14.325029720888354, "time_wass": 0.4698457298800349}