{"distribution": "nm", "edges": [["X", "Y"]], "root_params": ["X ~ B(0.8)"], "experiment": 2, "not_root_params": "P(Y|X) ~ N(21,10) if X = 0.0 and P(Y|X) ~ N(25,1) if X = 1.0", "sample_size": 500, "means": 21.8, "disc_method": "EB", "bins": 30, "target_column": null, "CPT_method": "Bayes", "time_disc": 0.03746860707178712, "time_cnf": 0.05169586278498173, "time_VE": 0.001154635101556778, "time_BP": 0.0031303120777010918, "RMSE": 0.3010667367375942, "WRMSE": 0.23644589777328037, "MAE": 0.27896029805141076, "PE": 9.420688473747692, "exact_EV": 21.8, "disc_EV": 23.853710087276998, "Wass_scaled": 0.008386791918757172, "Wass_multi": 0.3417262434081818, "time_wass": 0.07624615589156747}