{"distribution": "lg", "edges": [["A", "D"], ["B", "D"], ["D", "E"], ["C", "E"]], "root_params": "A ~ N(20,20) B ~ N(20,20) C ~ N(15,15)", "experiment": 110, "not_root_params": "D   ~   N ( 2 A + 3 B , 8 . 3 1 2 5 )   E   ~   N ( 3 C + 3 D , 8 . 3 1 2 5 )", "sample_size": 1406, "means": {"A": 20, "B": 20, "C": 15, "D": 100, "E": 345}, "disc_method": "EB", "bins": 17, "target_column": null, "CPT_method": "Bayespriors", "time_disc": 0.10246358998119831, "time_cnf": 0.27192486682906747, "time_VE": 0.0013130600564181805, "time_BP": 0.005704435985535383, "RMSE": 39.13356897024197, "WRMSE": 10.004429644524777, "MAE": 22.624003224907124, "PE": 0.4701095445418032, "exact_EV": 345, "disc_EV": 343.3781220713308, "Wass_scaled": 0.04292780421278367, "Wass_multi": 9.021674348948972, "time_wass": 0.6476629762910306}