{"distribution": "lg", "edges": [["A", "D"], ["B", "D"], ["D", "E"], ["C", "E"]], "root_params": "A ~ N(20,20) B ~ N(20,20) C ~ N(15,15)", "experiment": 104, "not_root_params": "D   ~   N ( 2 A + 3 B , 7 . 7 5 )   E   ~   N ( 3 C + 3 D , 7 . 7 5 )", "sample_size": 575, "means": {"A": 20, "B": 20, "C": 15, "D": 100, "E": 345}, "disc_method": "EV", "bins": 12, "target_column": null, "CPT_method": "MLE", "time_disc": 0.04981858795508742, "time_cnf": 0.3181439316831529, "time_VE": 0.001738283783197403, "time_BP": 0.00724297808483243, "RMSE": 5.87405897745586, "WRMSE": 5.8788864845944895, "MAE": 4.934771553555582, "PE": 0.9710002265547943, "exact_EV": 345, "disc_EV": 341.65004921838596, "Wass_scaled": 0.24676885268267196, "Wass_multi": 10.7703892329036, "time_wass": 0.3092945949174464}