{"distribution": "lg", "edges": [["A", "D"], ["B", "D"], ["D", "E"], ["C", "E"]], "root_params": "A ~ N(20,20) B ~ N(20,20) C ~ N(15,15)", "experiment": 122, "not_root_params": "D   ~   N ( 2 A + 3 B , 6 . 3 4 3 7 5 )   E   ~   N ( 3 C + 3 D , 6 . 3 4 3 7 5 )", "sample_size": 1941, "means": {"A": 20, "B": 20, "C": 15, "D": 100, "E": 345}, "disc_method": "EB", "bins": 12, "target_column": null, "CPT_method": "Bayespriors", "time_disc": 0.15404979999584612, "time_cnf": 0.05037689999153372, "time_VE": 0.001412099998560734, "time_BP": 0.01291740000306163, "RMSE": 36.83423760246138, "WRMSE": 7.487102226455456, "MAE": 20.308142644845212, "PE": 0.15715185158287767, "exact_EV": 345, "disc_EV": 344.4578261120391, "Wass_scaled": 0.06523770436876704, "Wass_multi": 11.73314607985518, "time_wass": 1.5501562999997986}