{"distribution": "lg", "edges": [["A", "D"], ["B", "D"], ["D", "E"], ["C", "E"]], "root_params": "A ~ N(20,20) B ~ N(20,20) C ~ N(15,15)", "experiment": 13, "not_root_params": "D   ~   N ( 2 A + 3 B , 2 )   E   ~   N ( 3 C + 3 D , 2 )", "sample_size": 800, "means": {"A": 20, "B": 20, "C": 15, "D": 100, "E": 345}, "disc_method": "EB", "bins": 20, "target_column": null, "CPT_method": "Bayes", "time_disc": 0.09971280000172555, "time_cnf": 0.18946320000395644, "time_VE": 0.0025239999959012493, "time_BP": 0.007256800003233366, "RMSE": 22.773653948581305, "WRMSE": 13.390990350033617, "MAE": 19.32034277794191, "PE": 1.5872937243168639, "exact_EV": 345, "disc_EV": 339.5238366511068, "Wass_scaled": 0.04044404774386279, "Wass_multi": 2.1889495212944547, "time_wass": 0.37406849999388214}