{"distribution": "lg", "edges": [["A", "D"], ["B", "D"], ["D", "E"], ["C", "E"]], "root_params": "A ~ N(20,20) B ~ N(20,20) C ~ N(15,15)", "experiment": 103, "not_root_params": "D   ~   N ( 2 A + 3 B , 3 . 2 5 )   E   ~   N ( 3 C + 3 D , 3 . 2 5 )", "sample_size": 1525, "means": {"A": 20, "B": 20, "C": 15, "D": 100, "E": 345}, "disc_method": "EV", "bins": 8, "target_column": null, "CPT_method": "Bayes", "time_disc": 0.07704125624150038, "time_cnf": 0.5941828014329076, "time_VE": 0.002024112269282341, "time_BP": 0.0078118667006492615, "RMSE": 8.577218111580029, "WRMSE": 8.582261874139789, "MAE": 6.939872867832875, "PE": 0.03477705343147979, "exact_EV": 345, "disc_EV": 344.8800191656614, "Wass_scaled": 0.32254892600573526, "Wass_multi": 6.15314016743039, "time_wass": 1.027090426068753}