{"distribution": "lg", "edges": [["A", "D"], ["B", "D"], ["D", "E"], ["C", "E"]], "root_params": "A ~ N(20,20) B ~ N(20,20) C ~ N(15,15)", "experiment": 12, "not_root_params": "D   ~   N ( 2 A + 3 B , 2 )   E   ~   N ( 3 C + 3 D , 2 )", "sample_size": 1000, "means": {"A": 20, "B": 20, "C": 15, "D": 100, "E": 345}, "disc_method": "EV", "bins": 5, "target_column": null, "CPT_method": "Bayes", "time_disc": 0.0880475000012666, "time_cnf": 0.008858899993356317, "time_VE": 0.001588999992236495, "time_BP": 0.009420499991392717, "RMSE": 3.6677521888709834, "WRMSE": 3.667752188870984, "MAE": 2.898619551244667, "PE": 0.06133773049574974, "exact_EV": 345, "disc_EV": 345.21161517021034, "Wass_scaled": 0.41555665039386336, "Wass_multi": 6.042951495485575, "time_wass": 0.5574450999993132}