{"distribution": "lg", "edges": [["A", "D"], ["B", "D"], ["D", "E"], ["C", "E"]], "root_params": "A ~ N(20,20) B ~ N(20,20) C ~ N(15,15)", "experiment": 13, "not_root_params": "D   ~   N ( 2 A + 3 B , 2 )   E   ~   N ( 3 C + 3 D , 2 )", "sample_size": 800, "means": {"A": 20, "B": 20, "C": 15, "D": 100, "E": 345}, "disc_method": "EB", "bins": 5, "target_column": null, "CPT_method": "Bayespriors", "time_disc": 0.1558727999945404, "time_cnf": 0.009497799997916445, "time_VE": 0.001382500006002374, "time_BP": 0.011439099995186552, "RMSE": 3.8494450781799614, "WRMSE": 2.320328074252116, "MAE": 3.345480812672008, "PE": 0.0058200629031608005, "exact_EV": 345, "disc_EV": 344.9799207829841, "Wass_scaled": 0.1681562365958872, "Wass_multi": 7.832601121294087, "time_wass": 0.3952119000023231}